feature_gate/__init__.py
feature_gate/adapters/memory.py
feature_gate/adapters/posthog.py
feature_gate/client.py
feature_gate/clients/posthog_api_client.py
feature_gate/feature.py
feature_gate-0.0.7.dist-info/LICENSE
feature_gate-0.0.7.dist-info/METADATA
feature_gate-0.0.7.dist-info/WHEEL
feature_gate-0.0.7.dist-info/RECORD
