Metadata-Version: 2.1
Name: feature_gate
Version: 0.0.7
Summary: An extensible feature flagging library for Python
Home-page: https://github.com/deftinc/feature_gate
License: MIT
Keywords: feature flags,feature gate
Author: Patrick Wiseman
Author-email: patrick@deft.services
Maintainer: Patrick Wiseman
Maintainer-email: patrick@deft.services
Requires-Python: >=3.10
Classifier: License :: OSI Approved :: MIT License
Classifier: Programming Language :: Python :: 3
Classifier: Programming Language :: Python :: 3.10
Classifier: Programming Language :: Python :: 3.11
Classifier: Programming Language :: Python :: 3.12
Requires-Dist: requests (>=2.31.0,<3.0.0)
Requires-Dist: structlog (>=24.1.0,<25.0.0)
Project-URL: Repository, https://github.com/deftinc/feature_gate
